ecallistolib/__init__.py
ecallistolib/combine.py
ecallistolib/crop.py
ecallistolib/download.py
ecallistolib/exceptions.py
ecallistolib/io.py
ecallistolib/models.py
ecallistolib/plotting.py
ecallistolib/processing.py
ecallistolib-0.2.3.1.dist-info/licenses/LICENSE
ecallistolib-0.2.3.1.dist-info/METADATA
ecallistolib-0.2.3.1.dist-info/WHEEL
ecallistolib-0.2.3.1.dist-info/top_level.txt
ecallistolib-0.2.3.1.dist-info/RECORD
