Metadata-Version: 2.4
Name: ecallistolib
Version: 0.2.3.1
Summary: Tools to download, read, process, and plot e-CALLISTO FITS dynamic spectra.
Author: Sahan S. Liyanage
License: MIT
Project-URL: Homepage, https://github.com/saandev/ecallistolib
Project-URL: Issues, https://github.com/saandev/ecallistolib/issues
Requires-Python: >=3.10
License-File: LICENSE
Requires-Dist: numpy>=1.23
Requires-Dist: astropy>=5.3
Provides-Extra: download
Requires-Dist: requests>=2.31; extra == "download"
Requires-Dist: beautifulsoup4>=4.12; extra == "download"
Provides-Extra: plot
Requires-Dist: matplotlib>=3.7; extra == "plot"
Dynamic: license-file
